odoo/addons/product_uom_updatable/README.rst
odoo/addons/product_uom_updatable/__init__.py
odoo/addons/product_uom_updatable/__manifest__.py
odoo/addons/product_uom_updatable/i18n/it.po
odoo/addons/product_uom_updatable/i18n/product_uom_updatable.pot
odoo/addons/product_uom_updatable/models/__init__.py
odoo/addons/product_uom_updatable/models/product_template.py
odoo/addons/product_uom_updatable/readme/CONTRIBUTORS.md
odoo/addons/product_uom_updatable/readme/CREDITS.md
odoo/addons/product_uom_updatable/readme/DESCRIPTION.md
odoo/addons/product_uom_updatable/static/description/icon.png
odoo/addons/product_uom_updatable/static/description/index.html
odoo/addons/product_uom_updatable/tests/__init__.py
odoo/addons/product_uom_updatable/tests/test_product_uom_update.py
odoo_addon_product_uom_updatable-18.0.1.0.0.2.dist-info/METADATA
odoo_addon_product_uom_updatable-18.0.1.0.0.2.dist-info/WHEEL
odoo_addon_product_uom_updatable-18.0.1.0.0.2.dist-info/top_level.txt
odoo_addon_product_uom_updatable-18.0.1.0.0.2.dist-info/RECORD
